cloudops/__init__.py
cloudops/google/__init__.py
cloudops/google/bigquery.py
cloudops/logging.py
cloudops_google_bigquery-0.1.4.dist-info/LICENSE
cloudops_google_bigquery-0.1.4.dist-info/WHEEL
cloudops_google_bigquery-0.1.4.dist-info/METADATA
cloudops_google_bigquery-0.1.4.dist-info/RECORD
