Metadata-Version: 2.1
Name: cloudops-google-bigquery
Version: 0.1.4
Summary: The cloudops-google-bigquery package
Home-page: https://github.com/manucalop/cloudops-google-bigquery
License: MIT
Author: Manuel Castillo
Author-email: manucalop@gmail.com
Requires-Python: >=3.9,<3.11
Classifier: License :: OSI Approved :: MIT License
Classifier: Programming Language :: Python :: 3
Classifier: Programming Language :: Python :: 3.9
Classifier: Programming Language :: Python :: 3.10
Requires-Dist: google-cloud-bigquery (>=3.1.0,<4.0.0)
Requires-Dist: pandas (>=1.4.2,<2.0.0)
Requires-Dist: pandas-gbq (>=0.17.5,<0.18.0)
Requires-Dist: pydantic (>=1.9.1,<2.0.0)
Project-URL: Repository, https://github.com/manucalop/cloudops-google-bigquery
